pyIMAPI.pyd
pyIMAPI2FSutil.dll
pyIMAPI-0.4.0b2.dist-info/METADATA
pyIMAPI-0.4.0b2.dist-info/RECORD
pyIMAPI-0.4.0b2.dist-info/WHEEL
pyIMAPI-0.4.0b2.dist-info/top_level.txt
